luigi_monkey_patch/__init__.py
luigi_monkey_patch-0.0.1.dist-info/DESCRIPTION.rst
luigi_monkey_patch-0.0.1.dist-info/METADATA
luigi_monkey_patch-0.0.1.dist-info/RECORD
luigi_monkey_patch-0.0.1.dist-info/WHEEL
luigi_monkey_patch-0.0.1.dist-info/metadata.json
luigi_monkey_patch-0.0.1.dist-info/top_level.txt
