Metadata-Version: 2.0
Name: luigi-monkey-patch
Version: 0.0.1
Summary: luigi monkey patch for large s3 file iteration
Home-page: https://github.com/zenixls2/luigi_monky_patch
Author: Zenix Huang
Author-email: zenixls2@gmail.com
License: Apache License 2.0
Keywords: patch luigi s3
Platform: UNKNOWN
Classifier: Development Status :: 5 - Production/Stable
Classifier: Environment :: Console
Classifier: Environment :: Web Environment
Classifier: Intended Audience :: Developers
Classifier: Intended Audience :: System Administrators
Classifier: License :: OSI Approved :: Apache Software License
Classifier: Programming Language :: Python :: 2.7
Classifier: Programming Language :: Python :: 3.3
Classifier: Programming Language :: Python :: 3.4
Classifier: Programming Language :: Python :: 3.5
Classifier: Topic :: System :: Monitoring
Requires-Dist: luigi
